dtos/__init__.py
dtos/__version__.py
dtos/crm_pkt_type.py
dtos/filter_info.py
dtos/host_info.py
dtos/host_type.py
dtos/metric_info.py
dtos/port_info.py
dtos/probe_ack.py
dtos/probe_init.py
dtos/register_ack.py
dtos/register_info.py
dtos/report_init.py
tl_crmdtos-1.0.0.dist-info/LICENSE
tl_crmdtos-1.0.0.dist-info/METADATA
tl_crmdtos-1.0.0.dist-info/WHEEL
tl_crmdtos-1.0.0.dist-info/top_level.txt
tl_crmdtos-1.0.0.dist-info/RECORD
