Metadata-Version: 2.1
Name: tl-crmdtos
Version: 1.0.0
Summary: DTOs used in cloudless resource monitoring system
Home-page: https://github.com/thanhledev/crm-dtos
Author: Thanh Le
Author-email: thanhledev@gmail.com
License: MIT
Platform: UNKNOWN
Classifier: License :: OSI Approved :: MIT License
Classifier: Programming Language :: Python
Classifier: Programming Language :: Python :: 3
Classifier: Programming Language :: Python :: 3.6
Requires-Python: >=3.6.0
